geode_explicitmodeling/__init__.py
geode_explicitmodeling/explicit_modeling2d.py
geode_explicitmodeling/explicit_modeling3d.py
geode_explicitmodeling/geode_explicitmodeling_py_explicit_modeling2d.cpython-39-x86_64-linux-gnu.so
geode_explicitmodeling/geode_explicitmodeling_py_explicit_modeling3d.cpython-39-x86_64-linux-gnu.so
geode_explicitmodeling/libGeode-ExplicitModeling_2d.so
geode_explicitmodeling/libGeode-ExplicitModeling_3d.so
geode_explicitmodeling/libGeode-ExplicitModeling_common.so
Geode_ExplicitModeling-2.3.10.dist-info/METADATA
Geode_ExplicitModeling-2.3.10.dist-info/WHEEL
Geode_ExplicitModeling-2.3.10.dist-info/top_level.txt
Geode_ExplicitModeling-2.3.10.dist-info/RECORD
