Metadata-Version: 2.1
Name: Geode-ExplicitModeling
Version: 2.3.10
Summary: Geode-solutions OpenGeode module for building explicit models
Home-page: https://github.com/Geode-solutions/Geode-ExplicitModeling
Author: Geode-solutions
Author-email: contact@geode-solutions.com
License: Proprietary
Requires-Dist: OpenGeode-core (==13.*,>=13.0.0)
Requires-Dist: OpenGeode-Inspector (==2.*,>=2.11.2)
Requires-Dist: Geode-Common (==24.*,>=24.0.0)
Requires-Dist: Geode-Conversion (==4.*,>=4.4.0)
Requires-Dist: Geode-BackgroundMesh (==6.*,>=6.0.0)
